mylib031/__init__.py
mylib_031-0.1.dist-info/LICENSE.txt
mylib_031-0.1.dist-info/METADATA
mylib_031-0.1.dist-info/WHEEL
mylib_031-0.1.dist-info/top_level.txt
mylib_031-0.1.dist-info/RECORD
