Metadata-Version: 2.1
Name: mylib-031
Version: 0.1
Summary: for check
Author: Rashed
Author-email: sdrashed2450@gmail.com
Classifier: Programming Language :: Python :: 3
Classifier: License :: OSI Approved :: MIT License
Classifier: Operating System :: OS Independent
License-File: LICENSE.txt
